binancetrading/__init__.py
binancetrading/account.py
binancetrading/backtest.py
binancetrading/command_line.py
binancetrading/exchange.py
binancetrading/orders.py
binancetrading/strategies.py
binancetrading/trading_bot.py
binancetrading/utils.py
binancetrading-0.0.1.dist-info/LICENSE.txt
binancetrading-0.0.1.dist-info/METADATA
binancetrading-0.0.1.dist-info/WHEEL
binancetrading-0.0.1.dist-info/top_level.txt
binancetrading-0.0.1.dist-info/RECORD
