Metadata-Version: 2.1
Name: binancetrading
Version: 0.0.1
Summary: Custom trading module using Binance API
Home-page: https://github.com/fegarciad/BinanceTrading
Author: Fernando Garcia
License: MIT License
Platform: UNKNOWN
Classifier: Programming Language :: Python :: 3
Classifier: License :: OSI Approved :: MIT License
Classifier: Operating System :: OS Independent
Requires-Python: >=3.7
License-File: LICENSE.txt
Requires-Dist: numpy
Requires-Dist: pandas
Requires-Dist: matplotlib
Requires-Dist: binance-connector
